{
    "name": "TradersGuild",
    "requierements": [
        {
            "type": "RESOURCE",
            "data": [
                {
                    "type": "ORE",
                    "quantity": 2
                },
                {
                    "type": "BRICK",
                    "quantity": 1
                },
                {
                    "type": "STONE",
                    "quantity": 1
                },
                {
                    "type": "WOOD",
                    "quantity": 1
                }
            ]
        }
    ],
    "age": 3,   
    "playersNeeded": 3,
     
    "effects": [
        {
            "type": "RESOURCEVICTORY",
            "data": {
                "ammount": 1,
                "direction": "BOTH"
            }
        }
    ]
}